LICENSE.txt
MANIFEST.in
README.rst
bootstrap.py
buildout.cfg
setup.py
versions.cfg
zinnia_html5/__init__.py
zinnia_html5/middleware.py
zinnia_html5/templates/zinnia/_entry_detail_base.html
zinnia_html5/templates/zinnia/base.html
zinnia_html5/templates/zinnia/entry_detail_base.html
zinnia_html5/templates/zinnia/skeleton.html
zinnia_html5/templates/zinnia/tags/breadcrumbs.html
zinnia_html5/templates/zinnia/tags/pagination.html
zinnia_theme_html5.egg-info/PKG-INFO
zinnia_theme_html5.egg-info/SOURCES.txt
zinnia_theme_html5.egg-info/dependency_links.txt
zinnia_theme_html5.egg-info/not-zip-safe
zinnia_theme_html5.egg-info/top_level.txt